fluidsf/__init__.py
fluidsf/bin_data.py
fluidsf/calculate_advection_2d.py
fluidsf/calculate_advection_3d.py
fluidsf/calculate_separation_distances.py
fluidsf/calculate_separation_distances_3d.py
fluidsf/calculate_sf_maps_2d.py
fluidsf/calculate_structure_function_1d.py
fluidsf/calculate_structure_function_2d.py
fluidsf/calculate_structure_function_3d.py
fluidsf/generate_sf_maps_2d.py
fluidsf/generate_structure_functions_1d.py
fluidsf/generate_structure_functions_2d.py
fluidsf/generate_structure_functions_3d.py
fluidsf/shift_array_1d.py
fluidsf/shift_array_2d.py
fluidsf/shift_array_3d.py
fluidsf/shift_array_xy.py
fluidsf-0.2.2.dist-info/licenses/LICENSE
fluidsf-0.2.2.dist-info/METADATA
fluidsf-0.2.2.dist-info/WHEEL
fluidsf-0.2.2.dist-info/top_level.txt
fluidsf-0.2.2.dist-info/RECORD
