Metadata-Version: 2.4
Name: fluidsf
Version: 0.2.2
Summary: Calculate structure functions from fluid data
Author-email: Cassidy Wagner <cassidymwagner@gmail.com>
Project-URL: Homepage, https://github.com/cassidymwagner/fluidsf
Project-URL: Bug Tracker, https://github.com/cassidymwagner/fluidsf/issues
Classifier: Programming Language :: Python :: 3
Classifier: License :: OSI Approved :: MIT License
Classifier: Operating System :: OS Independent
Requires-Python: >=3.7
License-File: LICENSE
Requires-Dist: numpy<3,>=1
Requires-Dist: pandas>=2.1.0
Requires-Dist: geopy>=2
Provides-Extra: test
Requires-Dist: pytest<8,>=7; extra == "test"
Provides-Extra: examples
Requires-Dist: matplotlib>=3.7.0; extra == "examples"
Requires-Dist: seaborn>=0.12.0; extra == "examples"
Requires-Dist: h5py>=3.10.0; extra == "examples"
Requires-Dist: scipy>=1.11.0; extra == "examples"
Requires-Dist: xarray>=2024.1.0; extra == "examples"
Requires-Dist: pooch>=1.8.0; extra == "examples"
Requires-Dist: h5netcdf>=1.3.0; extra == "examples"
Dynamic: license-file
